{
    "questionaryName": "gastro_date",
    "chapterOID": "chap_gastro_date",
    "chapterTitle": "chap_gastro_date",
    "estimatedTime": 1,
    "pricing": 1,
    "levelMax": "1",
    "authors": [
        "1"
    ],
    "professions": [
        "ENDOCRINOLOGY_DIABETOLOGY_NUTRITION"
    ],
    "companyId": [
        {}
    ],
    "linkedForm": "",
    "category": "HEALTH",
    "scoreStrategy": "SUM",
    "form": [
        {
            "formOID": "gastro_date",
            "formTitle": "gastro_date",
            "formDescription": "gastro_date"
        }
    ],
    "modules": [
        {
            "moduleOID": "gastro_date",
            "moduleTitle": "gastro_date",
            "questions": [
                {
                    "module": "",
                    "questionOID": "q_gastro_date_000",
                    "questionText": "En quelle année le diagnostic de cancer de l’œsophage a-t-il été posé la première fois ? ",
                    "type": "ANALOG_SCALE",
                    "isTriggered": true,
                    "triggeredQuestionOID": "",
                    "triggeredValue": 0,
                    "triggeredDefault": 0,
                    "tag": "",
                    "scope": "MODULE_SCOPE",
                    "isGlobal": false,
                    "isCalculation": false,
                    "calculation": [],
                    "isWithConditions": false,
                    "conditions": [],
                    "answers": [
                        {
                            "min": 1900,
                            "max": 2022,
                            "minText": "1900",
                            "midText": "",
                            "maxText": "Cette année",
                            "minValue": "1900",
                            "midValue": "",
                            "maxValue": 2022,
                            "step": 1,
                            "hideAnalogScaleSelectorNumber": false
                        }
                    ]
                },
                {
                    "module": "",
                    "questionOID": "q_gastro_date_001",
                    "questionText": "En quelle année le diagnostic de cancer de l’estomac a-t-il été posé la première fois ? ",
                    "type": "ANALOG_SCALE",
                    "isTriggered": false,
                    "triggeredQuestionOID": "q_gastro_date_000",
                    "triggeredValue": 0,
                    "triggeredDefault": 0,
                    "tag": "0",
                    "scope": "MODULE_SCOPE",
                    "isGlobal": false,
                    "isCalculation": false,
                    "calculation": [],
                    "isWithConditions": false,
                    "conditions": [],
                    "answers": [
                        {
                            "min": 1900,
                            "max": 2022,
                            "minText": "1900",
                            "midText": "",
                            "maxText": "Cette année",
                            "minValue": "1900",
                            "midValue": "",
                            "maxValue": 2022,
                            "step": 1,
                            "hideAnalogScaleSelectorNumber": false
                        }
                    ]
                },
                {
                    "module": "",
                    "questionOID": "q_gastro_date_002",
                    "questionText": "En quelle année le diagnostic de cancer du duodénum a-t-il été posé la première fois ? ",
                    "type": "ANALOG_SCALE",
                    "isTriggered": false,
                    "triggeredQuestionOID": "",
                    "triggeredValue": 0,
                    "triggeredDefault": 0,
                    "tag": "",
                    "scope": "MODULE_SCOPE",
                    "isGlobal": false,
                    "isCalculation": false,
                    "calculation": [],
                    "isWithConditions": false,
                    "conditions": [],
                    "answers": [
                        {
                            "min": 1900,
                            "max": 2022,
                            "minText": "1900",
                            "midText": "",
                            "maxText": "Cette année",
                            "minValue": "1900",
                            "midValue": "",
                            "maxValue": 2022,
                            "step": 1,
                            "hideAnalogScaleSelectorNumber": false
                        }
                    ]
                },
                {
                    "module": "",
                    "questionOID": "q_gastro_date_003",
                    "questionText": "En quelle année le diagnostic de cancer de l’intestin grêle a-t-il été posé la première fois ? ",
                    "type": "ANALOG_SCALE",
                    "isTriggered": false,
                    "triggeredQuestionOID": "",
                    "triggeredValue": 0,
                    "triggeredDefault": 0,
                    "tag": "",
                    "scope": "MODULE_SCOPE",
                    "isGlobal": false,
                    "isCalculation": false,
                    "calculation": [],
                    "isWithConditions": false,
                    "conditions": [],
                    "answers": [
                        {
                            "min": 1900,
                            "max": 2022,
                            "minText": "1900",
                            "midText": "",
                            "maxText": "Cette année",
                            "minValue": "1900",
                            "midValue": "",
                            "maxValue": 2022,
                            "step": 1,
                            "hideAnalogScaleSelectorNumber": false
                        }
                    ]
                },
                {
                    "module": "",
                    "questionOID": "q_gastro_date_004",
                    "questionText": "En quelle année le diagnostic de cancer du côlon a-t-il été posé la première fois ? ",
                    "type": "ANALOG_SCALE",
                    "isTriggered": false,
                    "triggeredQuestionOID": "",
                    "triggeredValue": 0,
                    "triggeredDefault": 0,
                    "tag": "",
                    "scope": "MODULE_SCOPE",
                    "isGlobal": false,
                    "isCalculation": false,
                    "calculation": [],
                    "isWithConditions": false,
                    "conditions": [],
                    "answers": [
                        {
                            "min": 1900,
                            "max": 2022,
                            "minText": "1900",
                            "midText": "",
                            "maxText": "Cette année",
                            "minValue": "1900",
                            "midValue": "",
                            "maxValue": 2022,
                            "step": 1,
                            "hideAnalogScaleSelectorNumber": false
                        }
                    ]
                },
                {
                    "module": "",
                    "questionOID": "q_gastro_date_005",
                    "questionText": "En quelle année le diagnostic de cancer du sigmoïde a-t-il été posé la première fois ? ",
                    "type": "ANALOG_SCALE",
                    "isTriggered": false,
                    "triggeredQuestionOID": "",
                    "triggeredValue": 0,
                    "triggeredDefault": 0,
                    "tag": "",
                    "scope": "MODULE_SCOPE",
                    "isGlobal": false,
                    "isCalculation": false,
                    "calculation": [],
                    "isWithConditions": false,
                    "conditions": [],
                    "answers": [
                        {
                            "min": 1900,
                            "max": 2022,
                            "minText": "1900",
                            "midText": "",
                            "maxText": "Cette année",
                            "minValue": "1900",
                            "midValue": "",
                            "maxValue": 2022,
                            "step": 1,
                            "hideAnalogScaleSelectorNumber": false
                        }
                    ]
                },
                {
                    "module": "",
                    "questionOID": "q_gastro_date_006",
                    "questionText": "En quelle année le diagnostic de cancer du rectum a-t-il été posé la première fois ? ",
                    "type": "ANALOG_SCALE",
                    "isTriggered": false,
                    "triggeredQuestionOID": "",
                    "triggeredValue": 0,
                    "triggeredDefault": 0,
                    "tag": "",
                    "scope": "MODULE_SCOPE",
                    "isGlobal": false,
                    "isCalculation": false,
                    "calculation": [],
                    "isWithConditions": false,
                    "conditions": [],
                    "answers": [
                        {
                            "min": 1900,
                            "max": 2022,
                            "minText": "1900",
                            "midText": "",
                            "maxText": "Cette année",
                            "minValue": "1900",
                            "midValue": "",
                            "maxValue": 2022,
                            "step": 1,
                            "hideAnalogScaleSelectorNumber": false
                        }
                    ]
                },
                {
                    "module": "",
                    "questionOID": "q_gastro_date_007",
                    "questionText": "En quelle année le diagnostic de cancer de l’anus a-t-il été posé la première fois ? ",
                    "type": "ANALOG_SCALE",
                    "isTriggered": false,
                    "triggeredQuestionOID": "",
                    "triggeredValue": 0,
                    "triggeredDefault": 0,
                    "tag": "",
                    "scope": "MODULE_SCOPE",
                    "isGlobal": false,
                    "isCalculation": false,
                    "calculation": [],
                    "isWithConditions": false,
                    "conditions": [],
                    "answers": [
                        {
                            "min": 1900,
                            "max": 2022,
                            "minText": "1900",
                            "midText": "",
                            "maxText": "Cette année",
                            "minValue": "1900",
                            "midValue": "",
                            "maxValue": 2022,
                            "step": 1,
                            "hideAnalogScaleSelectorNumber": false
                        }
                    ]
                },
                {
                    "module": "",
                    "questionOID": "q_gastro_date_008",
                    "questionText": "En quelle année le diagnostic de cancer du foie a-t-il été posé la première fois ? ",
                    "type": "ANALOG_SCALE",
                    "isTriggered": false,
                    "triggeredQuestionOID": "",
                    "triggeredValue": 0,
                    "triggeredDefault": 0,
                    "tag": "",
                    "scope": "MODULE_SCOPE",
                    "isGlobal": false,
                    "isCalculation": false,
                    "calculation": [],
                    "isWithConditions": false,
                    "conditions": [],
                    "answers": [
                        {
                            "min": 1900,
                            "max": 2022,
                            "minText": "1900",
                            "midText": "",
                            "maxText": "Cette année",
                            "minValue": "1900",
                            "midValue": "",
                            "maxValue": 2022,
                            "step": 1,
                            "hideAnalogScaleSelectorNumber": false
                        }
                    ]
                },
                {
                    "module": "",
                    "questionOID": "q_gastro_date_009",
                    "questionText": " En quelle année le diagnostic de cancer de la vésicule et/ou voies biliaires a-t-il été posé la première fois ? ",
                    "type": "ANALOG_SCALE",
                    "isTriggered": false,
                    "triggeredQuestionOID": "",
                    "triggeredValue": 0,
                    "triggeredDefault": 0,
                    "tag": "",
                    "scope": "MODULE_SCOPE",
                    "isGlobal": false,
                    "isCalculation": false,
                    "calculation": [],
                    "isWithConditions": false,
                    "conditions": [],
                    "answers": [
                        {
                            "min": 1900,
                            "max": 2022,
                            "minText": "1900",
                            "midText": "",
                            "maxText": "Cette année",
                            "minValue": "1900",
                            "midValue": "",
                            "maxValue": 2022,
                            "step": 1,
                            "hideAnalogScaleSelectorNumber": false
                        }
                    ]
                },
                {
                    "module": "",
                    "questionOID": "q_gastro_date_010",
                    "questionText": " En quelle année le diagnostic de cancer du pancréas a-t-il été posé la première fois ? ",
                    "type": "ANALOG_SCALE",
                    "isTriggered": false,
                    "triggeredQuestionOID": "",
                    "triggeredValue": 0,
                    "triggeredDefault": 0,
                    "tag": "",
                    "scope": "MODULE_SCOPE",
                    "isGlobal": false,
                    "isCalculation": false,
                    "calculation": [],
                    "isWithConditions": false,
                    "conditions": [],
                    "answers": [
                        {
                            "min": 1900,
                            "max": 2022,
                            "minText": "1900",
                            "midText": "",
                            "maxText": "Cette année",
                            "minValue": "1900",
                            "midValue": "",
                            "maxValue": 2022,
                            "step": 1,
                            "hideAnalogScaleSelectorNumber": false
                        }
                    ]
                },
                {
                    "module": "",
                    "questionOID": "q_gastro_date_011",
                    "questionText": "En quelle année le diagnostic d’œsophagite a-t-il été posé la première fois ? ",
                    "type": "ANALOG_SCALE",
                    "isTriggered": false,
                    "triggeredQuestionOID": "",
                    "triggeredValue": 0,
                    "triggeredDefault": 0,
                    "tag": "",
                    "scope": "MODULE_SCOPE",
                    "isGlobal": false,
                    "isCalculation": false,
                    "calculation": [],
                    "isWithConditions": false,
                    "conditions": [],
                    "answers": [
                        {
                            "min": 1900,
                            "max": 2022,
                            "minText": "1900",
                            "midText": "",
                            "maxText": "Cette année",
                            "minValue": "1900",
                            "midValue": "",
                            "maxValue": 2022,
                            "step": 1,
                            "hideAnalogScaleSelectorNumber": false
                        }
                    ]
                },
                {
                    "module": "",
                    "questionOID": "q_gastro_date_012",
                    "questionText": "En quelle année le diagnostic de reflux gastro-œsophagien a-t-il été posé la première fois ? ",
                    "type": "ANALOG_SCALE",
                    "isTriggered": false,
                    "triggeredQuestionOID": "",
                    "triggeredValue": 0,
                    "triggeredDefault": 0,
                    "tag": "",
                    "scope": "MODULE_SCOPE",
                    "isGlobal": false,
                    "isCalculation": false,
                    "calculation": [],
                    "isWithConditions": false,
                    "conditions": [],
                    "answers": [
                        {
                            "min": 1900,
                            "max": 2022,
                            "minText": "1900",
                            "midText": "",
                            "maxText": "Cette année",
                            "minValue": "1900",
                            "midValue": "",
                            "maxValue": 2022,
                            "step": 1,
                            "hideAnalogScaleSelectorNumber": false
                        }
                    ]
                },
                {
                    "module": "",
                    "questionOID": "q_gastro_date_013",
                    "questionText": "En quelle année le diagnostic de hernie hiatale a-t-il été posé la première fois ? ",
                    "type": "ANALOG_SCALE",
                    "isTriggered": false,
                    "triggeredQuestionOID": "",
                    "triggeredValue": 0,
                    "triggeredDefault": 0,
                    "tag": "",
                    "scope": "MODULE_SCOPE",
                    "isGlobal": false,
                    "isCalculation": false,
                    "calculation": [],
                    "isWithConditions": false,
                    "conditions": [],
                    "answers": [
                        {
                            "min": 1900,
                            "max": 2022,
                            "minText": "1900",
                            "midText": "",
                            "maxText": "Cette année",
                            "minValue": "1900",
                            "midValue": "",
                            "maxValue": 2022,
                            "step": 1,
                            "hideAnalogScaleSelectorNumber": false
                        }
                    ]
                },
                {
                    "module": "",
                    "questionOID": "q_gastro_date_014",
                    "questionText": "En quelle année le diagnostic de gastrite a-t-il été posé la première fois ? ",
                    "type": "ANALOG_SCALE",
                    "isTriggered": false,
                    "triggeredQuestionOID": "",
                    "triggeredValue": 0,
                    "triggeredDefault": 0,
                    "tag": "",
                    "scope": "MODULE_SCOPE",
                    "isGlobal": false,
                    "isCalculation": false,
                    "calculation": [],
                    "isWithConditions": false,
                    "conditions": [],
                    "answers": [
                        {
                            "min": 1900,
                            "max": 2022,
                            "minText": "1900",
                            "midText": "",
                            "maxText": "Cette année",
                            "minValue": "1900",
                            "midValue": "",
                            "maxValue": 2022,
                            "step": 1,
                            "hideAnalogScaleSelectorNumber": false
                        }
                    ]
                },
                {
                    "module": "",
                    "questionOID": "q_gastro_date_015",
                    "questionText": "En quelle année le diagnostic d’ulcère d’estomac a-t-il été posé la première fois ? ",
                    "type": "ANALOG_SCALE",
                    "isTriggered": false,
                    "triggeredQuestionOID": "",
                    "triggeredValue": 0,
                    "triggeredDefault": 0,
                    "tag": "",
                    "scope": "MODULE_SCOPE",
                    "isGlobal": false,
                    "isCalculation": false,
                    "calculation": [],
                    "isWithConditions": false,
                    "conditions": [],
                    "answers": [
                        {
                            "min": 1900,
                            "max": 2022,
                            "minText": "1900",
                            "midText": "",
                            "maxText": "Cette année",
                            "minValue": "1900",
                            "midValue": "",
                            "maxValue": 2022,
                            "step": 1,
                            "hideAnalogScaleSelectorNumber": false
                        }
                    ]
                },
                {
                    "module": "",
                    "questionOID": "q_gastro_date_016",
                    "questionText": "En quelle année le diagnostic d’ulcère du duodénum a-t-il été posé la première fois ? ",
                    "type": "ANALOG_SCALE",
                    "isTriggered": false,
                    "triggeredQuestionOID": "",
                    "triggeredValue": 0,
                    "triggeredDefault": 0,
                    "tag": "",
                    "scope": "MODULE_SCOPE",
                    "isGlobal": false,
                    "isCalculation": false,
                    "calculation": [],
                    "isWithConditions": false,
                    "conditions": [],
                    "answers": [
                        {
                            "min": 1900,
                            "max": 2022,
                            "minText": "1900",
                            "midText": "",
                            "maxText": "Cette année",
                            "minValue": "1900",
                            "midValue": "",
                            "maxValue": 2022,
                            "step": 1,
                            "hideAnalogScaleSelectorNumber": false
                        }
                    ]
                },
                {
                    "module": "",
                    "questionOID": "q_gastro_date_017",
                    "questionText": "En quelle année le diagnostic de duodénite a-t-il été posé la première fois ? ",
                    "type": "ANALOG_SCALE",
                    "isTriggered": false,
                    "triggeredQuestionOID": "",
                    "triggeredValue": 0,
                    "triggeredDefault": 0,
                    "tag": "",
                    "scope": "MODULE_SCOPE",
                    "isGlobal": false,
                    "isCalculation": false,
                    "calculation": [],
                    "isWithConditions": false,
                    "conditions": [],
                    "answers": [
                        {
                            "min": 1900,
                            "max": 2022,
                            "minText": "1900",
                            "midText": "",
                            "maxText": "Cette année",
                            "minValue": "1900",
                            "midValue": "",
                            "maxValue": 2022,
                            "step": 1,
                            "hideAnalogScaleSelectorNumber": false
                        }
                    ]
                },
                {
                    "module": "",
                    "questionOID": "q_gastro_date_018",
                    "questionText": "En quelle année le diagnostic de colopathie fonctionnelle a-t-il été posé la première fois ? ",
                    "type": "ANALOG_SCALE",
                    "isTriggered": false,
                    "triggeredQuestionOID": "",
                    "triggeredValue": 0,
                    "triggeredDefault": 0,
                    "tag": "",
                    "scope": "MODULE_SCOPE",
                    "isGlobal": false,
                    "isCalculation": false,
                    "calculation": [],
                    "isWithConditions": false,
                    "conditions": [],
                    "answers": [
                        {
                            "min": 1900,
                            "max": 2022,
                            "minText": "1900",
                            "midText": "",
                            "maxText": "Cette année",
                            "minValue": "1900",
                            "midValue": "",
                            "maxValue": 2022,
                            "step": 1,
                            "hideAnalogScaleSelectorNumber": false
                        }
                    ]
                },
                {
                    "module": "",
                    "questionOID": "q_gastro_date_019",
                    "questionText": "En quelle année le diagnostic de SIBO a-t-il été posé la première fois ? ",
                    "type": "ANALOG_SCALE",
                    "isTriggered": false,
                    "triggeredQuestionOID": "",
                    "triggeredValue": 0,
                    "triggeredDefault": 0,
                    "tag": "",
                    "scope": "MODULE_SCOPE",
                    "isGlobal": false,
                    "isCalculation": false,
                    "calculation": [],
                    "isWithConditions": false,
                    "conditions": [],
                    "answers": [
                        {
                            "min": 1900,
                            "max": 2022,
                            "minText": "1900",
                            "midText": "",
                            "maxText": "Cette année",
                            "minValue": "1900",
                            "midValue": "",
                            "maxValue": 2022,
                            "step": 1,
                            "hideAnalogScaleSelectorNumber": false
                        }
                    ]
                },
                {
                    "module": "",
                    "questionOID": "q_gastro_date_020",
                    "questionText": "En quelle année le diagnostic de polype a-t-il été posé la première fois ? ",
                    "type": "ANALOG_SCALE",
                    "isTriggered": false,
                    "triggeredQuestionOID": "",
                    "triggeredValue": 0,
                    "triggeredDefault": 0,
                    "tag": "",
                    "scope": "MODULE_SCOPE",
                    "isGlobal": false,
                    "isCalculation": false,
                    "calculation": [],
                    "isWithConditions": false,
                    "conditions": [],
                    "answers": [
                        {
                            "min": 1900,
                            "max": 2022,
                            "minText": "1900",
                            "midText": "",
                            "maxText": "Cette année",
                            "minValue": "1900",
                            "midValue": "",
                            "maxValue": 2022,
                            "step": 1,
                            "hideAnalogScaleSelectorNumber": false
                        }
                    ]
                },
                {
                    "module": "",
                    "questionOID": "q_gastro_date_021",
                    "questionText": "En quelle année le diagnostic de diverticulose a-t-il été posé la première fois ? ",
                    "type": "ANALOG_SCALE",
                    "isTriggered": false,
                    "triggeredQuestionOID": "",
                    "triggeredValue": 0,
                    "triggeredDefault": 0,
                    "tag": "",
                    "scope": "MODULE_SCOPE",
                    "isGlobal": false,
                    "isCalculation": false,
                    "calculation": [],
                    "isWithConditions": false,
                    "conditions": [],
                    "answers": [
                        {
                            "min": 1900,
                            "max": 2022,
                            "minText": "1900",
                            "midText": "",
                            "maxText": "Cette année",
                            "minValue": "1900",
                            "midValue": "",
                            "maxValue": 2022,
                            "step": 1,
                            "hideAnalogScaleSelectorNumber": false
                        }
                    ]
                },
                {
                    "module": "",
                    "questionOID": "q_gastro_date_022",
                    "questionText": "En quelle année le diagnostic de maladie de Crohn a-t-il été posé la première fois ? ",
                    "type": "ANALOG_SCALE",
                    "isTriggered": false,
                    "triggeredQuestionOID": "",
                    "triggeredValue": 0,
                    "triggeredDefault": 0,
                    "tag": "",
                    "scope": "MODULE_SCOPE",
                    "isGlobal": false,
                    "isCalculation": false,
                    "calculation": [],
                    "isWithConditions": false,
                    "conditions": [],
                    "answers": [
                        {
                            "min": 1900,
                            "max": 2022,
                            "minText": "1900",
                            "midText": "",
                            "maxText": "Cette année",
                            "minValue": "1900",
                            "midValue": "",
                            "maxValue": 2022,
                            "step": 1,
                            "hideAnalogScaleSelectorNumber": false
                        }
                    ]
                },
                {
                    "module": "",
                    "questionOID": "q_gastro_date_023",
                    "questionText": "En quelle année le diagnostic de recto-colite-hémorragique a-t-il été posé la première fois ? ",
                    "type": "ANALOG_SCALE",
                    "isTriggered": false,
                    "triggeredQuestionOID": "",
                    "triggeredValue": 0,
                    "triggeredDefault": 0,
                    "tag": "",
                    "scope": "MODULE_SCOPE",
                    "isGlobal": false,
                    "isCalculation": false,
                    "calculation": [],
                    "isWithConditions": false,
                    "conditions": [],
                    "answers": [
                        {
                            "min": 1900,
                            "max": 2022,
                            "minText": "1900",
                            "midText": "",
                            "maxText": "Cette année",
                            "minValue": "1900",
                            "midValue": "",
                            "maxValue": 2022,
                            "step": 1,
                            "hideAnalogScaleSelectorNumber": false
                        }
                    ]
                },
                {
                    "module": "",
                    "questionOID": "q_gastro_date_024",
                    "questionText": "En quelle année le diagnostic de colite pseudo-membraneuse a-t-il été posé la première fois ? ",
                    "type": "ANALOG_SCALE",
                    "isTriggered": false,
                    "triggeredQuestionOID": "",
                    "triggeredValue": 0,
                    "triggeredDefault": 0,
                    "tag": "",
                    "scope": "MODULE_SCOPE",
                    "isGlobal": false,
                    "isCalculation": false,
                    "calculation": [],
                    "isWithConditions": false,
                    "conditions": [],
                    "answers": [
                        {
                            "min": 1900,
                            "max": 2022,
                            "minText": "1900",
                            "midText": "",
                            "maxText": "Cette année",
                            "minValue": "1900",
                            "midValue": "",
                            "maxValue": 2022,
                            "step": 1,
                            "hideAnalogScaleSelectorNumber": false
                        }
                    ]
                },
                {
                    "module": "",
                    "questionOID": "q_gastro_date_025",
                    "questionText": "En quelle année le diagnostic d’hémorroïde a-t-il été posé la première fois ?  ",
                    "type": "ANALOG_SCALE",
                    "isTriggered": false,
                    "triggeredQuestionOID": "",
                    "triggeredValue": 0,
                    "triggeredDefault": 0,
                    "tag": "",
                    "scope": "MODULE_SCOPE",
                    "isGlobal": false,
                    "isCalculation": false,
                    "calculation": [],
                    "isWithConditions": false,
                    "conditions": [],
                    "answers": [
                        {
                            "min": 1900,
                            "max": 2022,
                            "minText": "1900",
                            "midText": "",
                            "maxText": "Cette année",
                            "minValue": "1900",
                            "midValue": "",
                            "maxValue": 2022,
                            "step": 1,
                            "hideAnalogScaleSelectorNumber": false
                        }
                    ]
                },
                {
                    "module": "",
                    "questionOID": "q_gastro_date_026",
                    "questionText": "En quelle année le diagnostic de fissure anale v été posé la première fois ? ",
                    "type": "ANALOG_SCALE",
                    "isTriggered": false,
                    "triggeredQuestionOID": "",
                    "triggeredValue": 0,
                    "triggeredDefault": 0,
                    "tag": "",
                    "scope": "MODULE_SCOPE",
                    "isGlobal": false,
                    "isCalculation": false,
                    "calculation": [],
                    "isWithConditions": false,
                    "conditions": [],
                    "answers": [
                        {
                            "min": 1900,
                            "max": 2022,
                            "minText": "1900",
                            "midText": "",
                            "maxText": "Cette année",
                            "minValue": "1900",
                            "midValue": "",
                            "maxValue": 2022,
                            "step": 1,
                            "hideAnalogScaleSelectorNumber": false
                        }
                    ]
                },
                {
                    "module": "",
                    "questionOID": "q_gastro_date_027",
                    "questionText": "En quelle année le diagnostic d’incontinence anale a-t-il été posé la première fois ? ",
                    "type": "ANALOG_SCALE",
                    "isTriggered": false,
                    "triggeredQuestionOID": "",
                    "triggeredValue": 0,
                    "triggeredDefault": 0,
                    "tag": "",
                    "scope": "MODULE_SCOPE",
                    "isGlobal": false,
                    "isCalculation": false,
                    "calculation": [],
                    "isWithConditions": false,
                    "conditions": [],
                    "answers": [
                        {
                            "min": 1900,
                            "max": 2022,
                            "minText": "1900",
                            "midText": "",
                            "maxText": "Cette année",
                            "minValue": "1900",
                            "midValue": "",
                            "maxValue": 2022,
                            "step": 1,
                            "hideAnalogScaleSelectorNumber": false
                        }
                    ]
                },
                {
                    "module": "",
                    "questionOID": "q_gastro_date_028",
                    "questionText": "En quelle année le diagnostic de stéatose hépatique a-t-il été posé la première fois ? ",
                    "type": "ANALOG_SCALE",
                    "isTriggered": false,
                    "triggeredQuestionOID": "",
                    "triggeredValue": 0,
                    "triggeredDefault": 0,
                    "tag": "",
                    "scope": "MODULE_SCOPE",
                    "isGlobal": false,
                    "isCalculation": false,
                    "calculation": [],
                    "isWithConditions": false,
                    "conditions": [],
                    "answers": [
                        {
                            "min": 1900,
                            "max": 2022,
                            "minText": "1900",
                            "midText": "",
                            "maxText": "Cette année",
                            "minValue": "1900",
                            "midValue": "",
                            "maxValue": 2022,
                            "step": 1,
                            "hideAnalogScaleSelectorNumber": false
                        }
                    ]
                },
                {
                    "module": "",
                    "questionOID": "q_gastro_date_029",
                    "questionText": "En quelle année le diagnostic de fibrose hépatique a-t-il été posé la première fois ? ",
                    "type": "ANALOG_SCALE",
                    "isTriggered": false,
                    "triggeredQuestionOID": "",
                    "triggeredValue": 0,
                    "triggeredDefault": 0,
                    "tag": "",
                    "scope": "MODULE_SCOPE",
                    "isGlobal": false,
                    "isCalculation": false,
                    "calculation": [],
                    "isWithConditions": false,
                    "conditions": [],
                    "answers": [
                        {
                            "min": 1900,
                            "max": 2022,
                            "minText": "1900",
                            "midText": "",
                            "maxText": "Cette année",
                            "minValue": "1900",
                            "midValue": "",
                            "maxValue": 2022,
                            "step": 1,
                            "hideAnalogScaleSelectorNumber": false
                        }
                    ]
                },
                {
                    "module": "",
                    "questionOID": "q_gastro_date_030",
                    "questionText": "En quelle année le diagnostic de cirrhose a-t-il été posé la première fois ? ",
                    "type": "ANALOG_SCALE",
                    "isTriggered": false,
                    "triggeredQuestionOID": "",
                    "triggeredValue": 0,
                    "triggeredDefault": 0,
                    "tag": "",
                    "scope": "MODULE_SCOPE",
                    "isGlobal": false,
                    "isCalculation": false,
                    "calculation": [],
                    "isWithConditions": false,
                    "conditions": [],
                    "answers": [
                        {
                            "min": 1900,
                            "max": 2022,
                            "minText": "1900",
                            "midText": "",
                            "maxText": "Cette année",
                            "minValue": "1900",
                            "midValue": "",
                            "maxValue": 2022,
                            "step": 1,
                            "hideAnalogScaleSelectorNumber": false
                        }
                    ]
                },
                {
                    "module": "",
                    "questionOID": "q_gastro_date_031",
                    "questionText": "En quelle année le diagnostic d’hépatite B a-t-il été posé la première fois ? ",
                    "type": "ANALOG_SCALE",
                    "isTriggered": false,
                    "triggeredQuestionOID": "",
                    "triggeredValue": 0,
                    "triggeredDefault": 0,
                    "tag": "",
                    "scope": "MODULE_SCOPE",
                    "isGlobal": false,
                    "isCalculation": false,
                    "calculation": [],
                    "isWithConditions": false,
                    "conditions": [],
                    "answers": [
                        {
                            "min": 1900,
                            "max": 2022,
                            "minText": "1900",
                            "midText": "",
                            "maxText": "Cette année",
                            "minValue": "1900",
                            "midValue": "",
                            "maxValue": 2022,
                            "step": 1,
                            "hideAnalogScaleSelectorNumber": false
                        }
                    ]
                },
                {
                    "module": "",
                    "questionOID": "q_gastro_date_032",
                    "questionText": "En quelle année le diagnostic d’hépatite C a-t-il été posé la première fois ? ",
                    "type": "ANALOG_SCALE",
                    "isTriggered": false,
                    "triggeredQuestionOID": "",
                    "triggeredValue": 0,
                    "triggeredDefault": 0,
                    "tag": "",
                    "scope": "MODULE_SCOPE",
                    "isGlobal": false,
                    "isCalculation": false,
                    "calculation": [],
                    "isWithConditions": false,
                    "conditions": [],
                    "answers": [
                        {
                            "min": 1900,
                            "max": 2022,
                            "minText": "1900",
                            "midText": "",
                            "maxText": "Cette année",
                            "minValue": "1900",
                            "midValue": "",
                            "maxValue": 2022,
                            "step": 1,
                            "hideAnalogScaleSelectorNumber": false
                        }
                    ]
                },
                {
                    "module": "",
                    "questionOID": "q_gastro_date_033",
                    "questionText": "En quelle année le diagnostic de cholangite a-t-il été posé la première fois ? ",
                    "type": "ANALOG_SCALE",
                    "isTriggered": false,
                    "triggeredQuestionOID": "",
                    "triggeredValue": 0,
                    "triggeredDefault": 0,
                    "tag": "",
                    "scope": "MODULE_SCOPE",
                    "isGlobal": false,
                    "isCalculation": false,
                    "calculation": [],
                    "isWithConditions": false,
                    "conditions": [],
                    "answers": [
                        {
                            "min": 1900,
                            "max": 2022,
                            "minText": "1900",
                            "midText": "",
                            "maxText": "Cette année",
                            "minValue": "1900",
                            "midValue": "",
                            "maxValue": 2022,
                            "step": 1,
                            "hideAnalogScaleSelectorNumber": false
                        }
                    ]
                },
                {
                    "module": "",
                    "questionOID": "q_gastro_date_034",
                    "questionText": "En quelle année le diagnostic de cholécystite a-t-il été posé la première fois ? ",
                    "type": "ANALOG_SCALE",
                    "isTriggered": false,
                    "triggeredQuestionOID": "",
                    "triggeredValue": 0,
                    "triggeredDefault": 0,
                    "tag": "",
                    "scope": "MODULE_SCOPE",
                    "isGlobal": false,
                    "isCalculation": false,
                    "calculation": [],
                    "isWithConditions": false,
                    "conditions": [],
                    "answers": [
                        {
                            "min": 1900,
                            "max": 2022,
                            "minText": "1900",
                            "midText": "",
                            "maxText": "Cette année",
                            "minValue": "1900",
                            "midValue": "",
                            "maxValue": 2022,
                            "step": 1,
                            "hideAnalogScaleSelectorNumber": false
                        }
                    ]
                },
                {
                    "module": "",
                    "questionOID": "q_gastro_date_035",
                    "questionText": "En quelle année le diagnostic de lithiase vésiculaire a-t-il été posé la première fois ? ",
                    "type": "ANALOG_SCALE",
                    "isTriggered": false,
                    "triggeredQuestionOID": "",
                    "triggeredValue": 0,
                    "triggeredDefault": 0,
                    "tag": "",
                    "scope": "MODULE_SCOPE",
                    "isGlobal": false,
                    "isCalculation": false,
                    "calculation": [],
                    "isWithConditions": false,
                    "conditions": [],
                    "answers": [
                        {
                            "min": 1900,
                            "max": 2022,
                            "minText": "1900",
                            "midText": "",
                            "maxText": "Cette année",
                            "minValue": "1900",
                            "midValue": "",
                            "maxValue": 2022,
                            "step": 1,
                            "hideAnalogScaleSelectorNumber": false
                        }
                    ]
                },
                {
                    "module": "",
                    "questionOID": "q_gastro_date_036",
                    "questionText": "En quelle année la cholécystectomie a-t-elle été pratiquée ? ",
                    "type": "ANALOG_SCALE",
                    "isTriggered": false,
                    "triggeredQuestionOID": "",
                    "triggeredValue": 0,
                    "triggeredDefault": 0,
                    "tag": "",
                    "scope": "MODULE_SCOPE",
                    "isGlobal": false,
                    "isCalculation": false,
                    "calculation": [],
                    "isWithConditions": false,
                    "conditions": [],
                    "answers": [
                        {
                            "min": 1900,
                            "max": 2022,
                            "minText": "1900",
                            "midText": "",
                            "maxText": "Cette année",
                            "minValue": "1900",
                            "midValue": "",
                            "maxValue": 2022,
                            "step": 1,
                            "hideAnalogScaleSelectorNumber": false
                        }
                    ]
                },
                {
                    "module": "",
                    "questionOID": "q_gastro_date_037",
                    "questionText": "En quelle année le diagnostic de pancréatite aigüe a-t-il été posé la première fois ? ",
                    "type": "ANALOG_SCALE",
                    "isTriggered": false,
                    "triggeredQuestionOID": "",
                    "triggeredValue": 0,
                    "triggeredDefault": 0,
                    "tag": "",
                    "scope": "MODULE_SCOPE",
                    "isGlobal": false,
                    "isCalculation": false,
                    "calculation": [],
                    "isWithConditions": false,
                    "conditions": [],
                    "answers": [
                        {
                            "min": 1900,
                            "max": 2022,
                            "minText": "1900",
                            "midText": "",
                            "maxText": "Cette année",
                            "minValue": "1900",
                            "midValue": "",
                            "maxValue": 2022,
                            "step": 1,
                            "hideAnalogScaleSelectorNumber": false
                        }
                    ]
                },
                {
                    "module": "",
                    "questionOID": "q_gastro_date_038",
                    "questionText": "En quelle année le diagnostic de pancréatite chronique a-t-il été posé la première fois ? ",
                    "type": "ANALOG_SCALE",
                    "isTriggered": false,
                    "triggeredQuestionOID": "",
                    "triggeredValue": 0,
                    "triggeredDefault": 0,
                    "tag": "",
                    "scope": "MODULE_SCOPE",
                    "isGlobal": false,
                    "isCalculation": false,
                    "calculation": [],
                    "isWithConditions": false,
                    "conditions": [],
                    "answers": [
                        {
                            "min": 1900,
                            "max": 2022,
                            "minText": "1900",
                            "midText": "",
                            "maxText": "Cette année",
                            "minValue": "1900",
                            "midValue": "",
                            "maxValue": 2022,
                            "step": 1,
                            "hideAnalogScaleSelectorNumber": false
                        }
                    ]
                },
                {
                    "module": "",
                    "questionOID": "q_gastro_date_039",
                    "questionText": "En quelle année le diagnostic de votre autre pathologie au niveau du foie, des voies biliaires ou du pancréas a-t-il été posé la première fois ? ",
                    "type": "ANALOG_SCALE",
                    "isTriggered": false,
                    "triggeredQuestionOID": "",
                    "triggeredValue": 0,
                    "triggeredDefault": 0,
                    "tag": "",
                    "scope": "MODULE_SCOPE",
                    "isGlobal": false,
                    "isCalculation": false,
                    "calculation": [],
                    "isWithConditions": false,
                    "conditions": [],
                    "answers": [
                        {
                            "min": 1900,
                            "max": 2022,
                            "minText": "1900",
                            "midText": "",
                            "maxText": "Cette année",
                            "minValue": "1900",
                            "midValue": "",
                            "maxValue": 2022,
                            "step": 1,
                            "hideAnalogScaleSelectorNumber": false
                        }
                    ]
                }
            ]
        }
    ],
    "tags": [
        {
            "tagOID": "0",
            "tagTitle": "0",
            "tagDescription": "0",
            "tagType": "SCORE",
            "sunburstName": "0",
            "module": "gastro_date",
            "rangeMin": [
                0,
                1
            ],
            "rangeMax": [
                0,
                1
            ],
            "parent": "",
            "children": []
        }
    ]
}
