{
  "oid": "q1_hemato-immuno",
  "title": "Q1 Global Focus Hématologie-Immunologie",
  "estimatedTime": 10,
  "pricing": 10,
  "description": "Q1 Global Focus Hématologie-Immunologie",
  "levelMax": "1",
  "authors": ["Jean-Philippe Astruc"],
  "chapters": ["chap_q1_hemato-immuno"],
  "professions": ["DENTIST"],
  "diagnostics": [],
  "reportingTrees": [
    {
      "category": "HEALTH",
      "scoreStrategy": "SUM",
      "reportingNode": {
        "tagOID": "S_HE_IM",
        "type": "SCORE",
        "ranges": [
          {
            "min": 0,
            "max": 0,
            "color": "00FF00",
            "text": "HEMAT-IMMU"
          },
          {
            "min": 1,
            "max": 1,
            "color": "FFFF00",
            "text": "HEMAT-IMMU"
          },
          {
            "min": 2,
            "max": 2,
            "color": "FF9900",
            "text": "HEMAT-IMMU"
          },
          {
            "min": 3,
            "max": 3,
            "color": "FF0000",
            "text": "HEMAT-IMMU"
          }
        ],
        "children": [
          {
            "tagOID": "S_HE_IM_ATCD_HEMATOLOGIE",
            "type": "SCORE",
            "ranges": [
              {
                "min": 0,
                "max": 0,
                "color": "00FF00",
                "text": "ATCD HEMAT"
              },
              {
                "min": 1,
                "max": 1,
                "color": "FF0000",
                "text": "ATCD HEMAT"
              }
            ],
            "children": [
              {
                "tagOID": "S_HE_IM_ATCD_HEMATOLOGIE_GR",
                "type": "SCORE",
                "ranges": [
                  {
                    "min": 0,
                    "max": 0,
                    "color": "00FF00",
                    "text": "ATCD GR"
                  },
                  {
                    "min": 1,
                    "max": 1,
                    "color": "FF0000",
                    "text": "ATCD GR"
                  }
                ],
                "children": [
                  {
                    "tagOID": "S_HE_IM_ATCD_HEMATOLOGIE_GR_FER",
                    "type": "SCORE",
                    "ranges": [
                      {
                        "min": 0,
                        "max": 0,
                        "color": "00FF00",
                        "text": "ANE FER"
                      },
                      {
                        "min": 1,
                        "max": 1,
                        "color": "FF0000",
                        "text": "ANE FER"
                      }
                    ],
                    "children": []
                  },
                  {
                    "tagOID": "S_HE_IM_ATCD_HEMATOLOGIE_GR_B9",
                    "type": "SCORE",
                    "ranges": [
                      {
                        "min": 0,
                        "max": 0,
                        "color": "00FF00",
                        "text": "ANE B9"
                      },
                      {
                        "min": 1,
                        "max": 1,
                        "color": "FF0000",
                        "text": "ANE B9"
                      }
                    ],
                    "children": []
                  },
                  {
                    "tagOID": "S_HE_IM_ATCD_HEMATOLOGIE_GR_B12",
                    "type": "SCORE",
                    "ranges": [
                      {
                        "min": 0,
                        "max": 0,
                        "color": "00FF00",
                        "text": "ANE B12"
                      },
                      {
                        "min": 1,
                        "max": 1,
                        "color": "FF0000",
                        "text": "ANE B12"
                      }
                    ],
                    "children": []
                  },
                  {
                    "tagOID": "S_HE_IM_ATCD_HEMATOLOGIE_GR_ANEMIE_INFLAMMATOIRE",
                    "type": "SCORE",
                    "ranges": [
                      {
                        "min": 0,
                        "max": 0,
                        "color": "00FF00",
                        "text": "ANE INFL"
                      },
                      {
                        "min": 1,
                        "max": 1,
                        "color": "FF0000",
                        "text": "ANE INFL"
                      }
                    ],
                    "children": []
                  },
                  {
                    "tagOID": "S_HE_IM_ATCD_HEMATOLOGIE_GR_ANEMIE_HEMOLYTIQUE",
                    "type": "SCORE",
                    "ranges": [
                      {
                        "min": 0,
                        "max": 0,
                        "color": "00FF00",
                        "text": "ANE HEMOL"
                      },
                      {
                        "min": 1,
                        "max": 1,
                        "color": "FF0000",
                        "text": "ANE HEMOL"
                      }
                    ],
                    "children": []
                  },
                  {
                    "tagOID": "S_HE_IM_ATCD_HEMATOLOGIE_GR_DREPANOCYTOSE",
                    "type": "SCORE",
                    "ranges": [
                      {
                        "min": 0,
                        "max": 0,
                        "color": "00FF00",
                        "text": "DREPANO"
                      },
                      {
                        "min": 1,
                        "max": 1,
                        "color": "FF0000",
                        "text": "DREPANO"
                      }
                    ],
                    "children": []
                  },
                  {
                    "tagOID": "S_HE_IM_ATCD_HEMATOLOGIE_GR_THALASSEMIE",
                    "type": "SCORE",
                    "ranges": [
                      {
                        "min": 0,
                        "max": 0,
                        "color": "00FF00",
                        "text": "THALAS"
                      },
                      {
                        "min": 1,
                        "max": 1,
                        "color": "FF0000",
                        "text": "THALAS"
                      }
                    ],
                    "children": []
                  },
                  {
                    "tagOID": "S_HE_IM_ATCD_HEMATOLOGIE_GR_MYELOFIBROSE",
                    "type": "SCORE",
                    "ranges": [
                      {
                        "min": 0,
                        "max": 0,
                        "color": "00FF00",
                        "text": "SPL MYELO"
                      },
                      {
                        "min": 1,
                        "max": 1,
                        "color": "FF0000",
                        "text": "SPL MYELO"
                      }
                    ],
                    "children": []
                  },
                  {
                    "tagOID": "S_HE_IM_ATCD_HEMATOLOGIE_GR_VAQUEZ",
                    "type": "SCORE",
                    "ranges": [
                      {
                        "min": 0,
                        "max": 0,
                        "color": "00FF00",
                        "text": "VAQUEZ"
                      },
                      {
                        "min": 1,
                        "max": 1,
                        "color": "FF0000",
                        "text": "VAQUEZ"
                      }
                    ],
                    "children": []
                  },
                  {
                    "tagOID": "S_HE_IM_ATCD_HEMATOLOGIE_GR_AUTRES",
                    "type": "SCORE",
                    "ranges": [
                      {
                        "min": 0,
                        "max": 0,
                        "color": "00FF00",
                        "text": "AUTRES"
                      },
                      {
                        "min": 1,
                        "max": 1,
                        "color": "FF0000",
                        "text": "AUTRES"
                      }
                    ],
                    "children": []
                  }
                ]
              },
              {
                "tagOID": "S_HE_IM_ATCD_HEMATOLOGIE_GB",
                "type": "SCORE",
                "ranges": [
                  {
                    "min": 0,
                    "max": 0,
                    "color": "00FF00",
                    "text": "ATCD GB"
                  },
                  {
                    "min": 1,
                    "max": 1,
                    "color": "FF0000",
                    "text": "ATCD GB"
                  }
                ],
                "children": [
                  {
                    "tagOID": "S_HE_IM_ATCD_HEMATOLOGIE_GB_LMC",
                    "type": "SCORE",
                    "ranges": [
                      {
                        "min": 0,
                        "max": 0,
                        "color": "00FF00",
                        "text": "LMC"
                      },
                      {
                        "min": 1,
                        "max": 1,
                        "color": "FF0000",
                        "text": "LMC"
                      }
                    ],
                    "children": []
                  },
                  {
                    "tagOID": "S_HE_IM_ATCD_HEMATOLOGIE_GB_LLC",
                    "type": "SCORE",
                    "ranges": [
                      {
                        "min": 0,
                        "max": 0,
                        "color": "00FF00",
                        "text": "LLC"
                      },
                      {
                        "min": 1,
                        "max": 1,
                        "color": "FF0000",
                        "text": "LLC"
                      }
                    ],
                    "children": []
                  },
                  {
                    "tagOID": "S_HE_IM_ATCD_HEMATOLOGIE_GB_LAM",
                    "type": "SCORE",
                    "ranges": [
                      {
                        "min": 0,
                        "max": 0,
                        "color": "00FF00",
                        "text": "LAM"
                      },
                      {
                        "min": 1,
                        "max": 1,
                        "color": "FF0000",
                        "text": "LAM"
                      }
                    ],
                    "children": []
                  },
                  {
                    "tagOID": "S_HE_IM_ATCD_HEMATOLOGIE_GB_LAL",
                    "type": "SCORE",
                    "ranges": [
                      {
                        "min": 0,
                        "max": 0,
                        "color": "00FF00",
                        "text": "LAL"
                      },
                      {
                        "min": 1,
                        "max": 1,
                        "color": "FF0000",
                        "text": "LAL"
                      }
                    ],
                    "children": []
                  },
                  {
                    "tagOID": "S_HE_IM_ATCD_HEMATOLOGIE_GB_LYMPHOME_HODGKINIEN",
                    "type": "SCORE",
                    "ranges": [
                      {
                        "min": 0,
                        "max": 0,
                        "color": "00FF00",
                        "text": "HODGKIN"
                      },
                      {
                        "min": 1,
                        "max": 1,
                        "color": "FF0000",
                        "text": "HODGKIN"
                      }
                    ],
                    "children": []
                  },
                  {
                    "tagOID": "S_HE_IM_ATCD_HEMATOLOGIE_GB_LYMPHOME_NON_HODGKINIEN",
                    "type": "SCORE",
                    "ranges": [
                      {
                        "min": 0,
                        "max": 0,
                        "color": "00FF00",
                        "text": "L NON HODG"
                      },
                      {
                        "min": 1,
                        "max": 1,
                        "color": "FF0000",
                        "text": "L NON HODG"
                      }
                    ],
                    "children": []
                  },
                  {
                    "tagOID": "S_HE_IM_ATCD_HEMATOLOGIE_GB_AUTRES",
                    "type": "SCORE",
                    "ranges": [
                      {
                        "min": 0,
                        "max": 0,
                        "color": "00FF00",
                        "text": "AUTRES"
                      },
                      {
                        "min": 1,
                        "max": 1,
                        "color": "FF0000",
                        "text": "AUTRES"
                      }
                    ],
                    "children": []
                  }
                ]
              },
              {
                "tagOID": "S_HE_IM_ATCD_HEMATOLOGIE_COAG",
                "type": "SCORE",
                "ranges": [
                  {
                    "min": 0,
                    "max": 0,
                    "color": "00FF00",
                    "text": "ATCD COAG"
                  },
                  {
                    "min": 1,
                    "max": 1,
                    "color": "FF0000",
                    "text": "ATCD COAG"
                  }
                ],
                "children": [
                  {
                    "tagOID": "S_HE_IM_ATCD_HEMATOLOGIE_COAG_THROMBOCYTEMIE",
                    "type": "SCORE",
                    "ranges": [
                      {
                        "min": 0,
                        "max": 0,
                        "color": "00FF00",
                        "text": "THROMBCYT"
                      },
                      {
                        "min": 1,
                        "max": 1,
                        "color": "FF0000",
                        "text": "THROMBCYT"
                      }
                    ],
                    "children": []
                  },
                  {
                    "tagOID": "S_HE_IM_ATCD_HEMATOLOGIE_COAG_THROMBOPENIE",
                    "type": "SCORE",
                    "ranges": [
                      {
                        "min": 0,
                        "max": 0,
                        "color": "00FF00",
                        "text": "THROMBOPEN"
                      },
                      {
                        "min": 1,
                        "max": 1,
                        "color": "FF0000",
                        "text": "THROMBOPEN"
                      }
                    ],
                    "children": []
                  },
                  {
                    "tagOID": "S_HE_IM_ATCD_HEMATOLOGIE_COAG_PURPURA_IDIOPATHIQUE",
                    "type": "SCORE",
                    "ranges": [
                      {
                        "min": 0,
                        "max": 0,
                        "color": "00FF00",
                        "text": "PURP THR IDIO"
                      },
                      {
                        "min": 1,
                        "max": 1,
                        "color": "FF0000",
                        "text": "PURP THR IDIO"
                      }
                    ],
                    "children": []
                  },
                  {
                    "tagOID": "S_HE_IM_ATCD_HEMATOLOGIE_COAG_WILLEBRAND",
                    "type": "SCORE",
                    "ranges": [
                      {
                        "min": 0,
                        "max": 0,
                        "color": "00FF00",
                        "text": "WILLEBRAND"
                      },
                      {
                        "min": 1,
                        "max": 1,
                        "color": "FF0000",
                        "text": "WILLEBRAND"
                      }
                    ],
                    "children": []
                  },
                  {
                    "tagOID": "S_HE_IM_ATCD_HEMATOLOGIE_COAG_PURPURA_THROMBOTIQUE",
                    "type": "SCORE",
                    "ranges": [
                      {
                        "min": 0,
                        "max": 0,
                        "color": "00FF00",
                        "text": "PURP THROMBOT"
                      },
                      {
                        "min": 1,
                        "max": 1,
                        "color": "FF0000",
                        "text": "PURP THROMBOT"
                      }
                    ],
                    "children": []
                  },
                  {
                    "tagOID": "S_HE_IM_ATCD_HEMATOLOGIE_COAG_HEMOPHILIE",
                    "type": "SCORE",
                    "ranges": [
                      {
                        "min": 0,
                        "max": 0,
                        "color": "00FF00",
                        "text": "HEMOPH"
                      },
                      {
                        "min": 1,
                        "max": 1,
                        "color": "FF0000",
                        "text": "HEMOPH"
                      }
                    ],
                    "children": []
                  },
                  {
                    "tagOID": "S_HE_IM_ATCD_HEMATOLOGIE_COAG_FACTEUR11",
                    "type": "SCORE",
                    "ranges": [
                      {
                        "min": 0,
                        "max": 0,
                        "color": "00FF00",
                        "text": "FACT 11"
                      },
                      {
                        "min": 1,
                        "max": 1,
                        "color": "FF0000",
                        "text": "FACT 11"
                      }
                    ],
                    "children": []
                  },
                  {
                    "tagOID": "S_HE_IM_ATCD_HEMATOLOGIE_COAG_FACTEUR5",
                    "type": "SCORE",
                    "ranges": [
                      {
                        "min": 0,
                        "max": 0,
                        "color": "00FF00",
                        "text": "FACT 5"
                      },
                      {
                        "min": 1,
                        "max": 1,
                        "color": "FF0000",
                        "text": "FACT 5"
                      }
                    ],
                    "children": []
                  },
                  {
                    "tagOID": "S_HE_IM_ATCD_HEMATOLOGIE_COAG_ANTITHROMBINE3",
                    "type": "SCORE",
                    "ranges": [
                      {
                        "min": 0,
                        "max": 0,
                        "color": "00FF00",
                        "text": "ANTI THROMB"
                      },
                      {
                        "min": 1,
                        "max": 1,
                        "color": "FF0000",
                        "text": "ANTI THROMB"
                      }
                    ],
                    "children": []
                  },
                  {
                    "tagOID": "S_HE_IM_ATCD_HEMATOLOGIE_COAG_PROT_C",
                    "type": "SCORE",
                    "ranges": [
                      {
                        "min": 0,
                        "max": 0,
                        "color": "00FF00",
                        "text": "PROT C"
                      },
                      {
                        "min": 1,
                        "max": 1,
                        "color": "FF0000",
                        "text": "PROT C"
                      }
                    ],
                    "children": []
                  },
                  {
                    "tagOID": "S_HE_IM_ATCD_HEMATOLOGIE_COAG_PROT_S",
                    "type": "SCORE",
                    "ranges": [
                      {
                        "min": 0,
                        "max": 0,
                        "color": "00FF00",
                        "text": "PROT S"
                      },
                      {
                        "min": 1,
                        "max": 1,
                        "color": "FF0000",
                        "text": "PROT S"
                      }
                    ],
                    "children": []
                  },
                  {
                    "tagOID": "S_HE_IM_ATCD_HEMATOLOGIE_COAG_AUTRES",
                    "type": "SCORE",
                    "ranges": [
                      {
                        "min": 0,
                        "max": 0,
                        "color": "00FF00",
                        "text": "AUTRES"
                      },
                      {
                        "min": 1,
                        "max": 1,
                        "color": "FF0000",
                        "text": "AUTRES"
                      }
                    ],
                    "children": []
                  }
                ]
              }
            ]
          },
          {
            "tagOID": "S_HE_IM_ATCD_IMMUNO",
            "type": "SCORE",
            "ranges": [
              {
                "min": 0,
                "max": 0,
                "color": "00FF00",
                "text": "ATCD IMMUNO"
              },
              {
                "min": 1,
                "max": 1,
                "color": "FF0000",
                "text": "ATCD IMMUNO"
              }
            ],
            "children": [
              {
                "tagOID": "S_HE_IM_ATCD_IMMUNO_CANCER",
                "type": "SCORE",
                "ranges": [
                  {
                    "min": 0,
                    "max": 0,
                    "color": "00FF00",
                    "text": "ATCD CANCER"
                  },
                  {
                    "min": 1,
                    "max": 1,
                    "color": "FF0000",
                    "text": "ATCD CANCER"
                  }
                ],
                "children": [
                  {
                    "tagOID": "S_HE_IM_ATCD_IMMUNO_CANCER_TRAITEMENT",
                    "type": "SCORE",
                    "ranges": [
                      {
                        "min": 0,
                        "max": 0,
                        "color": "00FF00",
                        "text": "KC TRAITEMENT"
                      },
                      {
                        "min": 1,
                        "max": 1,
                        "color": "FF0000",
                        "text": "KC TRAITEMENT"
                      }
                    ],
                    "children": [
                      {
                        "tagOID": "S_HE_IM_ATCD_IMMUNO_CANCER_TRAITEMENT_CHIRURGIE",
                        "type": "SCORE",
                        "ranges": [
                          {
                            "min": 0,
                            "max": 0,
                            "color": "00FF00",
                            "text": "CHIR"
                          },
                          {
                            "min": 1,
                            "max": 1,
                            "color": "FF0000",
                            "text": "CHIR"
                          }
                        ],
                        "children": []
                      },
                      {
                        "tagOID": "S_HE_IM_ATCD_IMMUNO_CANCER_TRAITEMENT_RADIOTHERAPIE",
                        "type": "SCORE",
                        "ranges": [
                          {
                            "min": 0,
                            "max": 0,
                            "color": "00FF00",
                            "text": "RADIOTH"
                          },
                          {
                            "min": 1,
                            "max": 1,
                            "color": "FF0000",
                            "text": "RADIOTH"
                          }
                        ],
                        "children": []
                      },
                      {
                        "tagOID": "S_HE_IM_ATCD_IMMUNO_CANCER_TRAITEMENT_CHIMIOTHERAPIE",
                        "type": "SCORE",
                        "ranges": [
                          {
                            "min": 0,
                            "max": 0,
                            "color": "00FF00",
                            "text": "CHIMIO"
                          },
                          {
                            "min": 1,
                            "max": 1,
                            "color": "FF0000",
                            "text": "CHIMIO"
                          }
                        ],
                        "children": []
                      },
                      {
                        "tagOID": "S_HE_IM_ATCD_IMMUNO_CANCER_TRAITEMENT_THERAPIES_CIBLEES",
                        "type": "SCORE",
                        "ranges": [
                          {
                            "min": 0,
                            "max": 0,
                            "color": "00FF00",
                            "text": "THER CIBL"
                          },
                          {
                            "min": 1,
                            "max": 1,
                            "color": "FF0000",
                            "text": "THER CIBL"
                          }
                        ],
                        "children": []
                      },
                      {
                        "tagOID": "S_HE_IM_ATCD_IMMUNO_CANCER_TRAITEMENT_HORMONOTHERAPIE",
                        "type": "SCORE",
                        "ranges": [
                          {
                            "min": 0,
                            "max": 0,
                            "color": "00FF00",
                            "text": "HORMONOTH"
                          },
                          {
                            "min": 1,
                            "max": 1,
                            "color": "FF0000",
                            "text": "HORMONOTH"
                          }
                        ],
                        "children": []
                      },
                      {
                        "tagOID": "S_HE_IM_ATCD_IMMUNO_CANCER_TRAITEMENT_IMMUNOTHERAPIE",
                        "type": "SCORE",
                        "ranges": [
                          {
                            "min": 0,
                            "max": 0,
                            "color": "00FF00",
                            "text": "IMMUNOTH"
                          },
                          {
                            "min": 1,
                            "max": 1,
                            "color": "FF0000",
                            "text": "IMMUNOTH"
                          }
                        ],
                        "children": []
                      },
                      {
                        "tagOID": "S_HE_IM_ATCD_IMMUNO_CANCER_TRAITEMENT_CURIETHERAPIE",
                        "type": "SCORE",
                        "ranges": [
                          {
                            "min": 0,
                            "max": 0,
                            "color": "00FF00",
                            "text": "CURIETH"
                          },
                          {
                            "min": 1,
                            "max": 1,
                            "color": "FF0000",
                            "text": "CURIETH"
                          }
                        ],
                        "children": []
                      },
                      {
                        "tagOID": "S_HE_IM_ATCD_IMMUNO_CANCER_TRAITEMENT_GREFFE_MOELLE",
                        "type": "SCORE",
                        "ranges": [
                          {
                            "min": 0,
                            "max": 0,
                            "color": "00FF00",
                            "text": "GREF MOELLE"
                          },
                          {
                            "min": 1,
                            "max": 1,
                            "color": "FF0000",
                            "text": "GREF MOELLE"
                          }
                        ],
                        "children": []
                      },
                      {
                        "tagOID": "S_HE_IM_ATCD_IMMUNO_CANCER_TRAITEMENT_EFFACE",
                        "type": "SCORE",
                        "ranges": [
                          {
                            "min": 0,
                            "max": 0,
                            "color": "00FF00",
                            "text": "EFFACE"
                          },
                          {
                            "min": 1,
                            "max": 1,
                            "color": "FF0000",
                            "text": "EFFACE"
                          }
                        ],
                        "children": []
                      },
                      {
                        "tagOID": "S_HE_IM_ATCD_IMMUNO_CANCER_TRAITEMENT_EFFACE2",
                        "type": "SCORE",
                        "ranges": [
                          {
                            "min": 0,
                            "max": 0,
                            "color": "00FF00",
                            "text": "EFF"
                          },
                          {
                            "min": 1,
                            "max": 1,
                            "color": "FF0000",
                            "text": "EFF"
                          }
                        ],
                        "children": []
                      }
                    ]
                  }
                ]
              },
              {
                "tagOID": "S_HE_IM_ATCD_IMMUNO_MAI",
                "type": "SCORE",
                "ranges": [
                  {
                    "min": 0,
                    "max": 0,
                    "color": "00FF00",
                    "text": "ATCD MAI"
                  },
                  {
                    "min": 1,
                    "max": 1,
                    "color": "FF0000",
                    "text": "ATCD MAI"
                  }
                ],
                "children": [
                  {
                    "tagOID": "S_HE_IM_ATCD_IMMUNO_MAI_TYPE_LUPUS",
                    "type": "SCORE",
                    "ranges": [
                      {
                        "min": 0,
                        "max": 0,
                        "color": "00FF00",
                        "text": "LED"
                      },
                      {
                        "min": 1,
                        "max": 1,
                        "color": "FF0000",
                        "text": "LED"
                      }
                    ],
                    "children": []
                  },
                  {
                    "tagOID": "S_HE_IM_ATCD_IMMUNO_MAI_TYPE_SCLERODERMIE",
                    "type": "SCORE",
                    "ranges": [
                      {
                        "min": 0,
                        "max": 0,
                        "color": "00FF00",
                        "text": "SCLERODER"
                      },
                      {
                        "min": 1,
                        "max": 1,
                        "color": "FF0000",
                        "text": "SCLERODER"
                      }
                    ],
                    "children": []
                  },
                  {
                    "tagOID": "S_HE_IM_ATCD_IMMUNO_MAI_TYPE_SHARP",
                    "type": "SCORE",
                    "ranges": [
                      {
                        "min": 0,
                        "max": 0,
                        "color": "00FF00",
                        "text": "SHARP"
                      },
                      {
                        "min": 1,
                        "max": 1,
                        "color": "FF0000",
                        "text": "SHARP"
                      }
                    ],
                    "children": []
                  },
                  {
                    "tagOID": "S_HE_IM_ATCD_IMMUNO_MAI_TYPE_SJOGREN",
                    "type": "SCORE",
                    "ranges": [
                      {
                        "min": 0,
                        "max": 0,
                        "color": "00FF00",
                        "text": "SJOGREN"
                      },
                      {
                        "min": 1,
                        "max": 1,
                        "color": "FF0000",
                        "text": "SJOGREN"
                      }
                    ],
                    "children": []
                  },
                  {
                    "tagOID": "S_HE_IM_ATCD_IMMUNO_MAI_TYPE_BEHCET",
                    "type": "SCORE",
                    "ranges": [
                      {
                        "min": 0,
                        "max": 0,
                        "color": "00FF00",
                        "text": "BEHCET"
                      },
                      {
                        "min": 1,
                        "max": 1,
                        "color": "FF0000",
                        "text": "BEHCET"
                      }
                    ],
                    "children": []
                  },
                  {
                    "tagOID": "S_HE_IM_ATCD_IMMUNO_MAI_TYPE_VASCULARITE",
                    "type": "SCORE",
                    "ranges": [
                      {
                        "min": 0,
                        "max": 0,
                        "color": "00FF00",
                        "text": "VASCUL"
                      },
                      {
                        "min": 1,
                        "max": 1,
                        "color": "FF0000",
                        "text": "VASCUL"
                      }
                    ],
                    "children": []
                  },
                  {
                    "tagOID": "S_HE_IM_ATCD_IMMUNO_MAI_TYPE_SARCOIDOSE",
                    "type": "SCORE",
                    "ranges": [
                      {
                        "min": 0,
                        "max": 0,
                        "color": "00FF00",
                        "text": "SARCOID"
                      },
                      {
                        "min": 1,
                        "max": 1,
                        "color": "FF0000",
                        "text": "SARCOID"
                      }
                    ],
                    "children": []
                  },
                  {
                    "tagOID": "S_HE_IM_ATCD_IMMUNO_MAI_MALADIE_PERIODIQUE",
                    "type": "SCORE",
                    "ranges": [
                      {
                        "min": 0,
                        "max": 0,
                        "color": "00FF00",
                        "text": "MAL PERIOD"
                      },
                      {
                        "min": 1,
                        "max": 1,
                        "color": "FF0000",
                        "text": "MAL PERIOD"
                      }
                    ],
                    "children": []
                  },
                  {
                    "tagOID": "S_HE_IM_ATCD_IMMUNO_MAI_TYPE_AUTRE",
                    "type": "SCORE",
                    "ranges": [
                      {
                        "min": 0,
                        "max": 0,
                        "color": "00FF00",
                        "text": "AUTRES"
                      },
                      {
                        "min": 1,
                        "max": 1,
                        "color": "FF0000",
                        "text": "AUTRES"
                      }
                    ],
                    "children": []
                  },
                  {
                    "tagOID": "S_HE_IM_ATCD_IMMUNO_MAI_TRAITEMENT_IMMUNO",
                    "type": "SCORE",
                    "ranges": [
                      {
                        "min": 0,
                        "max": 3,
                        "color": "00FF00",
                        "text": "TRT ACTUEL"
                      },
                      {
                        "min": 2,
                        "max": 2,
                        "color": "FF0000",
                        "text": "TRT ACTUEL"
                      }
                    ],
                    "children": []
                  }
                ]
              },
              {
                "tagOID": "S_HE_IM_ATCD_IMMUNO_ALLERGIE",
                "type": "SCORE",
                "ranges": [
                  {
                    "min": 0,
                    "max": 0,
                    "color": "00FF00",
                    "text": "ATCD ALLERG"
                  },
                  {
                    "min": 1,
                    "max": 1,
                    "color": "FF0000",
                    "text": "ATCD ALLERG"
                  }
                ],
                "children": [
                  {
                    "tagOID": "S_HE_IM_ATCD_IMMUNO_ALLERGIE_COELIAQUE",
                    "type": "SCORE",
                    "ranges": [
                      {
                        "min": 0,
                        "max": 0,
                        "color": "00FF00",
                        "text": "COELIAQ"
                      },
                      {
                        "min": 1,
                        "max": 1,
                        "color": "FF0000",
                        "text": "COELIAQ"
                      }
                    ],
                    "children": []
                  },
                  {
                    "tagOID": "S_HE_IM_ATCD_IMMUNO_ALLERGIE_ALIMENT",
                    "type": "SCORE",
                    "ranges": [
                      {
                        "min": 0,
                        "max": 0,
                        "color": "00FF00",
                        "text": "ALIM"
                      },
                      {
                        "min": 1,
                        "max": 1,
                        "color": "FF0000",
                        "text": "ALIM"
                      }
                    ],
                    "children": []
                  },
                  {
                    "tagOID": "S_HE_IM_ATCD_IMMUNO_ALLERGIE_ACARIENS",
                    "type": "SCORE",
                    "ranges": [
                      {
                        "min": 0,
                        "max": 0,
                        "color": "00FF00",
                        "text": "ACARIEN"
                      },
                      {
                        "min": 1,
                        "max": 1,
                        "color": "FF0000",
                        "text": "ACARIEN"
                      }
                    ],
                    "children": []
                  },
                  {
                    "tagOID": "S_HE_IM_ATCD_IMMUNO_ALLERGIE_POIL",
                    "type": "SCORE",
                    "ranges": [
                      {
                        "min": 0,
                        "max": 0,
                        "color": "00FF00",
                        "text": "POIL"
                      },
                      {
                        "min": 1,
                        "max": 1,
                        "color": "FF0000",
                        "text": "POIL"
                      }
                    ],
                    "children": []
                  },
                  {
                    "tagOID": "S_HE_IM_ATCD_IMMUNO_ALLERGIE_GRAMINES",
                    "type": "SCORE",
                    "ranges": [
                      {
                        "min": 0,
                        "max": 0,
                        "color": "00FF00",
                        "text": "GRAM-POLL"
                      },
                      {
                        "min": 1,
                        "max": 1,
                        "color": "FF0000",
                        "text": "GRAM-POLL"
                      }
                    ],
                    "children": []
                  },
                  {
                    "tagOID": "S_HE_IM_ATCD_IMMUNO_ALLERGIE_CONTACT",
                    "type": "SCORE",
                    "ranges": [
                      {
                        "min": 0,
                        "max": 0,
                        "color": "00FF00",
                        "text": "CONTACT"
                      },
                      {
                        "min": 1,
                        "max": 1,
                        "color": "FF0000",
                        "text": "CONTACT"
                      }
                    ],
                    "children": []
                  },
                  {
                    "tagOID": "S_HE_IM_ATCD_IMMUNO_ALLERGIE_MEDICAMENT",
                    "type": "SCORE",
                    "ranges": [
                      {
                        "min": 0,
                        "max": 0,
                        "color": "00FF00",
                        "text": "MEDIC"
                      },
                      {
                        "min": 1,
                        "max": 1,
                        "color": "FF0000",
                        "text": "MEDIC"
                      }
                    ],
                    "children": []
                  },
                  {
                    "tagOID": "S_HE_IM_ATCD_IMMUNO_ALLERGIE_AUTRES",
                    "type": "SCORE",
                    "ranges": [
                      {
                        "min": 0,
                        "max": 0,
                        "color": "00FF00",
                        "text": "AUTRES"
                      },
                      {
                        "min": 1,
                        "max": 1,
                        "color": "FF0000",
                        "text": "AUTRES"
                      }
                    ],
                    "children": []
                  }
                ]
              },
              {
                "tagOID": "S_HE_IM_ATCD_IMMUNO_INFECTION",
                "type": "SCORE",
                "ranges": [
                  {
                    "min": 0,
                    "max": 0,
                    "color": "00FF00",
                    "text": "ATCD INFECT"
                  },
                  {
                    "min": 1,
                    "max": 1,
                    "color": "FF0000",
                    "text": "ATCD INFECT"
                  }
                ],
                "children": [
                  {
                    "tagOID": "S_HE_IM_ATCD_IMMUNO_INFECTION_DEFICIT_IMMUNI_PRIMITIF",
                    "type": "SCORE",
                    "ranges": [
                      {
                        "min": 0,
                        "max": 0,
                        "color": "00FF00",
                        "text": "DEF IMM PRIM"
                      },
                      {
                        "min": 1,
                        "max": 1,
                        "color": "FF0000",
                        "text": "DEF IMM PRIM"
                      }
                    ],
                    "children": []
                  },
                  {
                    "tagOID": "S_HE_IM_ATCD_IMMUNO_INFECTION_PLASMOCYTES",
                    "type": "SCORE",
                    "ranges": [
                      {
                        "min": 0,
                        "max": 0,
                        "color": "00FF00",
                        "text": "PLASMOC"
                      },
                      {
                        "min": 1,
                        "max": 1,
                        "color": "FF0000",
                        "text": "PLASMOC"
                      }
                    ],
                    "children": []
                  },
                  {
                    "tagOID": "S_HE_IM_ATCD_IMMUNO_INFECTION_VIH",
                    "type": "SCORE",
                    "ranges": [
                      {
                        "min": 0,
                        "max": 0,
                        "color": "00FF00",
                        "text": "VIH"
                      },
                      {
                        "min": 1,
                        "max": 1,
                        "color": "FF0000",
                        "text": "VIH"
                      }
                    ],
                    "children": []
                  },
                  {
                    "tagOID": "S_HE_IM_ATCD_IMMUNO_INFECTION_OSLER",
                    "type": "SCORE",
                    "ranges": [
                      {
                        "min": 0,
                        "max": 0,
                        "color": "00FF00",
                        "text": "OSLER"
                      },
                      {
                        "min": 1,
                        "max": 1,
                        "color": "FF0000",
                        "text": "OSLER"
                      }
                    ],
                    "children": []
                  },
                  {
                    "tagOID": "S_HE_IM_ATCD_IMMUNO_INFECTION_HERPES1",
                    "type": "SCORE",
                    "ranges": [
                      {
                        "min": 0,
                        "max": 0,
                        "color": "00FF00",
                        "text": "HERPES 1"
                      },
                      {
                        "min": 1,
                        "max": 1,
                        "color": "FF0000",
                        "text": "HERPES 1"
                      }
                    ],
                    "children": []
                  },
                  {
                    "tagOID": "S_HE_IM_ATCD_IMMUNO_INFECTION_CMV",
                    "type": "SCORE",
                    "ranges": [
                      {
                        "min": 0,
                        "max": 0,
                        "color": "00FF00",
                        "text": "CMV"
                      },
                      {
                        "min": 1,
                        "max": 1,
                        "color": "FF0000",
                        "text": "CMV"
                      }
                    ],
                    "children": []
                  },
                  {
                    "tagOID": "S_HE_IM_ATCD_IMMUNO_INFECTION_VZV",
                    "type": "SCORE",
                    "ranges": [
                      {
                        "min": 0,
                        "max": 0,
                        "color": "00FF00",
                        "text": "VZV"
                      },
                      {
                        "min": 1,
                        "max": 1,
                        "color": "FF0000",
                        "text": "VZV"
                      }
                    ],
                    "children": []
                  },
                  {
                    "tagOID": "S_HE_IM_ATCD_IMMUNO_INFECTION_ROUGEOLE",
                    "type": "SCORE",
                    "ranges": [
                      {
                        "min": 0,
                        "max": 0,
                        "color": "00FF00",
                        "text": "ROUGEOLE"
                      },
                      {
                        "min": 1,
                        "max": 1,
                        "color": "FF0000",
                        "text": "ROUGEOLE"
                      }
                    ],
                    "children": []
                  },
                  {
                    "tagOID": "S_HE_IM_ATCD_IMMUNO_INFECTION_OREILLONS",
                    "type": "SCORE",
                    "ranges": [
                      {
                        "min": 0,
                        "max": 0,
                        "color": "00FF00",
                        "text": "OREILLONS"
                      },
                      {
                        "min": 1,
                        "max": 1,
                        "color": "FF0000",
                        "text": "OREILLONS"
                      }
                    ],
                    "children": []
                  },
                  {
                    "tagOID": "S_HE_IM_ATCD_IMMUNO_INFECTION_RUBEOLE",
                    "type": "SCORE",
                    "ranges": [
                      {
                        "min": 0,
                        "max": 0,
                        "color": "00FF00",
                        "text": "RUBEOLE"
                      },
                      {
                        "min": 1,
                        "max": 1,
                        "color": "FF0000",
                        "text": "RUBEOLE"
                      }
                    ],
                    "children": []
                  },
                  {
                    "tagOID": "S_HE_IM_ATCD_IMMUNO_INFECTION_PAPILLOMAVIRUS",
                    "type": "SCORE",
                    "ranges": [
                      {
                        "min": 0,
                        "max": 0,
                        "color": "00FF00",
                        "text": "PVH"
                      },
                      {
                        "min": 1,
                        "max": 1,
                        "color": "FF0000",
                        "text": "PVH"
                      }
                    ],
                    "children": []
                  },
                  {
                    "tagOID": "S_HE_IM_ATCD_IMMUNO_INFECTION_ASPERGILLOSE",
                    "type": "SCORE",
                    "ranges": [
                      {
                        "min": 0,
                        "max": 0,
                        "color": "00FF00",
                        "text": "ASPERG"
                      },
                      {
                        "min": 1,
                        "max": 1,
                        "color": "FF0000",
                        "text": "ASPERG"
                      }
                    ],
                    "children": []
                  },
                  {
                    "tagOID": "S_HE_IM_ATCD_IMMUNO_INFECTION_LYME",
                    "type": "SCORE",
                    "ranges": [
                      {
                        "min": 0,
                        "max": 0,
                        "color": "00FF00",
                        "text": "LYME"
                      },
                      {
                        "min": 1,
                        "max": 1,
                        "color": "FF0000",
                        "text": "LYME"
                      }
                    ],
                    "children": []
                  },
                  {
                    "tagOID": "S_HE_IM_ATCD_IMMUNO_INFECTION_MENINGITE",
                    "type": "SCORE",
                    "ranges": [
                      {
                        "min": 0,
                        "max": 0,
                        "color": "00FF00",
                        "text": "MENINGO"
                      },
                      {
                        "min": 1,
                        "max": 1,
                        "color": "FF0000",
                        "text": "MENINGO"
                      }
                    ],
                    "children": []
                  },
                  {
                    "tagOID": "S_HE_IM_ATCD_IMMUNO_INFECTION_TOXOPLASMOSE",
                    "type": "SCORE",
                    "ranges": [
                      {
                        "min": 0,
                        "max": 0,
                        "color": "00FF00",
                        "text": "TOXO"
                      },
                      {
                        "min": 1,
                        "max": 1,
                        "color": "FF0000",
                        "text": "TOXO"
                      }
                    ],
                    "children": []
                  },
                  {
                    "tagOID": "S_HE_IM_ATCD_IMMUNO_INFECTION_AMIBIASE",
                    "type": "SCORE",
                    "ranges": [
                      {
                        "min": 0,
                        "max": 0,
                        "color": "00FF00",
                        "text": "AMIBIASE"
                      },
                      {
                        "min": 1,
                        "max": 1,
                        "color": "FF0000",
                        "text": "AMIBIASE"
                      }
                    ],
                    "children": []
                  },
                  {
                    "tagOID": "S_HE_IM_ATCD_IMMUNO_INFECTION_GIARDIASE",
                    "type": "SCORE",
                    "ranges": [
                      {
                        "min": 0,
                        "max": 0,
                        "color": "00FF00",
                        "text": "GIARDIASE"
                      },
                      {
                        "min": 1,
                        "max": 1,
                        "color": "FF0000",
                        "text": "GIARDIASE"
                      }
                    ],
                    "children": []
                  },
                  {
                    "tagOID": "S_HE_IM_ATCD_IMMUNO_INFECTION_PALUDISME",
                    "type": "SCORE",
                    "ranges": [
                      {
                        "min": 0,
                        "max": 0,
                        "color": "00FF00",
                        "text": "PALU"
                      },
                      {
                        "min": 1,
                        "max": 1,
                        "color": "FF0000",
                        "text": "PALU"
                      }
                    ],
                    "children": []
                  }
                ]
              }
            ]
          }
        ]
      }
    }
  ]
}
