{
  "oid": "q_q2_contexte_de_vie_020",
  "title": "Avez-vous ces six derniers mois (et ce, de façon plus importante qu’avant) perdu vos affaires plus souvent et/ou plus longtemps que d’habitude ?",
  "text": "Avez-vous ces six derniers mois (et ce, de façon plus importante qu’avant) perdu vos affaires plus souvent et/ou plus longtemps que d’habitude ?",
  "type": "SINGLE_CHOICE_RADIO",
  "choices": [
    {
      "code": "1",
      "text": "Oui"
    },
    {
      "code": "0",
      "text": "Non"
    }
  ],
  "scores": [
    {
      "conditions": "q_q2_contexte_de_vie_020 == \"0\"",
      "tagOID": "S_N_PREDICTIF_QPC",
      "value": 0
    },
    {
      "conditions": "q_q2_contexte_de_vie_020 == \"1\"",
      "tagOID": "S_N_PREDICTIF_QPC",
      "value": 1
    }
  ]
}