{
  "oid": "mod_TCI",
  "title": "mod TCI",
  "questions": [
    { "question": "VPETCI001", "level": 1 },
    { "question": "VPETCI002", "level": 1 },
    { "question": "VPETCI003", "level": 1 },
    { "question": "VPETCI004", "level": 1 },
    { "question": "VPETCI005", "level": 1 },
    { "question": "VPETCI006", "level": 1 },
    { "question": "VPETCI007", "level": 1 },
    { "question": "VPETCI008", "level": 1 },
    { "question": "VPETCI009", "level": 1 },
    { "question": "VPETCI010", "level": 1 },
    { "question": "VPETCI011", "level": 1 },
    { "question": "VPETCI012", "level": 1 },
    { "question": "VPETCI013", "level": 1 },
    { "question": "VPETCI014", "level": 1 },
    { "question": "VPETCI015", "level": 1 },
    { "question": "VPETCI016", "level": 1 },
    { "question": "VPETCI017", "level": 1 },
    { "question": "VPETCI018", "level": 1 },
    { "question": "VPETCI019", "level": 1 },
    { "question": "VPETCI020", "level": 1 },
    { "question": "VPETCI021", "level": 1 },
    { "question": "VPETCI022", "level": 1 },
    { "question": "VPETCI023", "level": 1 },
    { "question": "VPETCI024", "level": 1 },
    { "question": "VPETCI025", "level": 1 },
    { "question": "VPETCI026", "level": 1 },
    { "question": "VPETCI027", "level": 1 },
    { "question": "VPETCI028", "level": 1 },
    { "question": "VPETCI029", "level": 1 },
    { "question": "VPETCI030", "level": 1 },
    { "question": "VPETCI031", "level": 1 },
    { "question": "VPETCI032", "level": 1 },
    { "question": "VPETCI033", "level": 1 },
    { "question": "VPETCI034", "level": 1 },
    { "question": "VPETCI035", "level": 1 },
    { "question": "VPETCI036", "level": 1 },
    { "question": "VPETCI037", "level": 1 },
    { "question": "VPETCI038", "level": 1 },
    { "question": "VPETCI039", "level": 1 },
    { "question": "VPETCI040", "level": 1 },
    { "question": "VPETCI041", "level": 1 },
    { "question": "VPETCI042", "level": 1 },
    { "question": "VPETCI043", "level": 1 },
    { "question": "VPETCI044", "level": 1 },
    { "question": "VPETCI045", "level": 1 },
    { "question": "VPETCI046", "level": 1 },
    { "question": "VPETCI047", "level": 1 },
    { "question": "VPETCI048", "level": 1 },
    { "question": "VPETCI049", "level": 1 },
    { "question": "VPETCI050", "level": 1 },
    { "question": "VPETCI051", "level": 1 },
    { "question": "VPETCI052", "level": 1 },
    { "question": "VPETCI053", "level": 1 },
    { "question": "VPETCI054", "level": 1 },
    { "question": "VPETCI055", "level": 1 },
    { "question": "VPETCI056", "level": 1 },
    { "question": "VPETCI057", "level": 1 },
    { "question": "VPETCI058", "level": 1 },
    { "question": "VPETCI059", "level": 1 },
    { "question": "VPETCI060", "level": 1 },
    { "question": "VPETCI061", "level": 1 },
    { "question": "VPETCI062", "level": 1 },
    { "question": "VPETCI063", "level": 1 },
    { "question": "VPETCI064", "level": 1 },
    { "question": "VPETCI065", "level": 1 },
    { "question": "VPETCI066", "level": 1 },
    { "question": "VPETCI067", "level": 1 },
    { "question": "VPETCI068", "level": 1 },
    { "question": "VPETCI069", "level": 1 },
    { "question": "VPETCI070", "level": 1 },
    { "question": "VPETCI071", "level": 1 },
    { "question": "VPETCI072", "level": 1 },
    { "question": "VPETCI073", "level": 1 },
    { "question": "VPETCI074", "level": 1 },
    { "question": "VPETCI075", "level": 1 },
    { "question": "VPETCI076", "level": 1 },
    { "question": "VPETCI077", "level": 1 },
    { "question": "VPETCI078", "level": 1 },
    { "question": "VPETCI079", "level": 1 },
    { "question": "VPETCI080", "level": 1 },
    { "question": "VPETCI081", "level": 1 },
    { "question": "VPETCI082", "level": 1 },
    { "question": "VPETCI083", "level": 1 },
    { "question": "VPETCI084", "level": 1 },
    { "question": "VPETCI085", "level": 1 },
    { "question": "VPETCI086", "level": 1 },
    { "question": "VPETCI087", "level": 1 },
    { "question": "VPETCI088", "level": 1 },
    { "question": "VPETCI089", "level": 1 },
    { "question": "VPETCI090", "level": 1 },
    { "question": "VPETCI091", "level": 1 },
    { "question": "VPETCI092", "level": 1 },
    { "question": "VPETCI093", "level": 1 },
    { "question": "VPETCI094", "level": 1 },
    { "question": "VPETCI095", "level": 1 },
    { "question": "VPETCI096", "level": 1 },
    { "question": "VPETCI097", "level": 1 },
    { "question": "VPETCI098", "level": 1 },
    { "question": "VPETCI099", "level": 1 },
    { "question": "VPETCI100", "level": 1 },
    { "question": "VPETCI101", "level": 1 },
    { "question": "VPETCI102", "level": 1 },
    { "question": "VPETCI103", "level": 1 },
    { "question": "VPETCI104", "level": 1 },
    { "question": "VPETCI105", "level": 1 },
    { "question": "VPETCI106", "level": 1 },
    { "question": "VPETCI107", "level": 1 },
    { "question": "VPETCI108", "level": 1 },
    { "question": "VPETCI109", "level": 1 },
    { "question": "VPETCI110", "level": 1 },
    { "question": "VPETCI111", "level": 1 },
    { "question": "VPETCI112", "level": 1 },
    { "question": "VPETCI113", "level": 1 },
    { "question": "VPETCI114", "level": 1 },
    { "question": "VPETCI115", "level": 1 },
    { "question": "VPETCI116", "level": 1 },
    { "question": "VPETCI117", "level": 1 },
    { "question": "VPETCI118", "level": 1 },
    { "question": "VPETCI119", "level": 1 },
    { "question": "VPETCI120", "level": 1 },
    { "question": "VPETCI121", "level": 1 },
    { "question": "VPETCI122", "level": 1 },
    { "question": "VPETCI123", "level": 1 },
    { "question": "VPETCI124", "level": 1 },
    { "question": "VPETCI125", "level": 1 },
    { "question": "VPETCI126", "level": 1 },
    { "question": "VPETCI127", "level": 1 },
    { "question": "VPETCI128", "level": 1 },
    { "question": "VPETCI129", "level": 1 },
    { "question": "VPETCI130", "level": 1 },
    { "question": "VPETCI131", "level": 1 },
    { "question": "VPETCI132", "level": 1 },
    { "question": "VPETCI133", "level": 1 },
    { "question": "VPETCI134", "level": 1 },
    { "question": "VPETCI135", "level": 1 },
    { "question": "VPETCI136", "level": 1 },
    { "question": "VPETCI137", "level": 1 },
    { "question": "VPETCI138", "level": 1 },
    { "question": "VPETCI139", "level": 1 },
    { "question": "VPETCI140", "level": 1 },
    { "question": "VPETCI141", "level": 1 },
    { "question": "VPETCI142", "level": 1 },
    { "question": "VPETCI143", "level": 1 },
    { "question": "VPETCI144", "level": 1 },
    { "question": "VPETCI145", "level": 1 },
    { "question": "VPETCI146", "level": 1 },
    { "question": "VPETCI147", "level": 1 },
    { "question": "VPETCI148", "level": 1 },
    { "question": "VPETCI149", "level": 1 },
    { "question": "VPETCI150", "level": 1 },
    { "question": "VPETCI151", "level": 1 },
    { "question": "VPETCI152", "level": 1 },
    { "question": "VPETCI153", "level": 1 },
    { "question": "VPETCI154", "level": 1 },
    { "question": "VPETCI155", "level": 1 },
    { "question": "VPETCI156", "level": 1 },
    { "question": "VPETCI157", "level": 1 },
    { "question": "VPETCI158", "level": 1 },
    { "question": "VPETCI159", "level": 1 },
    { "question": "VPETCI160", "level": 1 },
    { "question": "VPETCI161", "level": 1 },
    { "question": "VPETCI162", "level": 1 },
    { "question": "VPETCI163", "level": 1 },
    { "question": "VPETCI164", "level": 1 },
    { "question": "VPETCI165", "level": 1 },
    { "question": "VPETCI166", "level": 1 },
    { "question": "VPETCI167", "level": 1 },
    { "question": "VPETCI168", "level": 1 },
    { "question": "VPETCI169", "level": 1 },
    { "question": "VPETCI170", "level": 1 },
    { "question": "VPETCI171", "level": 1 },
    { "question": "VPETCI172", "level": 1 },
    { "question": "VPETCI173", "level": 1 },
    { "question": "VPETCI174", "level": 1 },
    { "question": "VPETCI175", "level": 1 },
    { "question": "VPETCI176", "level": 1 },
    { "question": "VPETCI177", "level": 1 },
    { "question": "VPETCI178", "level": 1 },
    { "question": "VPETCI179", "level": 1 },
    { "question": "VPETCI180", "level": 1 },
    { "question": "VPETCI181", "level": 1 },
    { "question": "VPETCI182", "level": 1 },
    { "question": "VPETCI183", "level": 1 },
    { "question": "VPETCI184", "level": 1 },
    { "question": "VPETCI185", "level": 1 },
    { "question": "VPETCI186", "level": 1 },
    { "question": "VPETCI187", "level": 1 },
    { "question": "VPETCI188", "level": 1 },
    { "question": "VPETCI189", "level": 1 },
    { "question": "VPETCI190", "level": 1 },
    { "question": "VPETCI191", "level": 1 },
    { "question": "VPETCI192", "level": 1 },
    { "question": "VPETCI193", "level": 1 },
    { "question": "VPETCI194", "level": 1 },
    { "question": "VPETCI195", "level": 1 },
    { "question": "VPETCI196", "level": 1 },
    { "question": "VPETCI197", "level": 1 },
    { "question": "VPETCI198", "level": 1 },
    { "question": "VPETCI199", "level": 1 },
    { "question": "VPETCI200", "level": 1 },
    { "question": "VPETCI201", "level": 1 },
    { "question": "VPETCI202", "level": 1 },
    { "question": "VPETCI203", "level": 1 },
    { "question": "VPETCI204", "level": 1 },
    { "question": "VPETCI205", "level": 1 },
    { "question": "VPETCI206", "level": 1 },
    { "question": "VPETCI207", "level": 1 },
    { "question": "VPETCI208", "level": 1 },
    { "question": "VPETCI209", "level": 1 },
    { "question": "VPETCI210", "level": 1 },
    { "question": "VPETCI211", "level": 1 },
    { "question": "VPETCI212", "level": 1 },
    { "question": "VPETCI213", "level": 1 },
    { "question": "VPETCI214", "level": 1 },
    { "question": "VPETCI215", "level": 1 },
    { "question": "VPETCI216", "level": 1 },
    { "question": "VPETCI217", "level": 1 },
    { "question": "VPETCI218", "level": 1 },
    { "question": "VPETCI219", "level": 1 },
    { "question": "VPETCI220", "level": 1 },
    { "question": "VPETCI221", "level": 1 },
    { "question": "VPETCI222", "level": 1 },
    { "question": "VPETCI223", "level": 1 },
    { "question": "VPETCI224", "level": 1 },
    { "question": "VPETCI225", "level": 1 },
    { "question": "VPETCI226", "level": 1 }
  ]
}
