{
  "oid": "TETE",
  "title": "TETE",
  "questions": [
    {
      "question": "q_VTeteCouleur",
      "level": 1,
      "isGlobal": false
    },
    {
      "question": "q_VTeteTensionEmotionnelle",
      "level": 1,
      "isGlobal": false
    },
    {
      "question": "q_VTeteAnxieteTrait",
      "level": 1,
      "isGlobal": false
    },
    {
      "question": "q_VTetePerfectionnisme",
      "level": 1,
      "isGlobal": false
    },
    {
      "question": "q_VTeteStressGlobal",
      "level": 1,
      "isGlobal": false
    },
    {
      "question": "q_VTeteMotivationStade",
      "level": 1,
      "isGlobal": false
    },
    {
      "question": "q_VTeteMotivationEnvie",
      "level": 1,
      "isGlobal": false
    },
    {
      "question": "q_VTeteMotivationConfiance",
      "level": 1,
      "isGlobal": false
    },
    {
      "question": "q_VTeteMotivationPret",
      "level": 1,
      "isGlobal": false
    },
    {
      "question": "q_VTeteVisionSoiGlobale",
      "level": 1,
      "isGlobal": false
    },
    {
      "question": "q_VTeteImageCorporelle",
      "level": 1,
      "isGlobal": false
    },
    {
      "question": "q_VTeteADSGlobale",
      "level": 1,
      "isGlobal": false
    },
    {
      "question": "q_VTeteConfianceSoi",
      "level": 1,
      "isGlobal": false
    },
    {
      "question": "q_VTeteEstimeSoi",
      "level": 1,
      "isGlobal": false
    }
  ]
}